deteasypaddleocr/__init__.py
deteasypaddleocr/config.json
deteasypaddleocr/ocr_detection.py
deteasypaddleocr/custom_easyocr/__init__.py
deteasypaddleocr/custom_easyocr/config.py
deteasypaddleocr/custom_easyocr/craft.py
deteasypaddleocr/custom_easyocr/craft_utils.py
deteasypaddleocr/custom_easyocr/detection.py
deteasypaddleocr/custom_easyocr/detection_db.py
deteasypaddleocr/custom_easyocr/easyocr_custom_lib.py
deteasypaddleocr/custom_easyocr/utils.py
deteasypaddleocr/custom_easyocr/DBNet/DBNet.py
deteasypaddleocr/custom_easyocr/DBNet/README.md
deteasypaddleocr/custom_easyocr/DBNet/assets/ops/dcn/__init__.py
deteasypaddleocr/custom_easyocr/DBNet/assets/ops/dcn/setup.py
deteasypaddleocr/custom_easyocr/DBNet/assets/ops/dcn/functions/__init__.py
deteasypaddleocr/custom_easyocr/DBNet/assets/ops/dcn/functions/deform_conv.py
deteasypaddleocr/custom_easyocr/DBNet/assets/ops/dcn/functions/deform_pool.py
deteasypaddleocr/custom_easyocr/DBNet/assets/ops/dcn/modules/__init__.py
deteasypaddleocr/custom_easyocr/DBNet/assets/ops/dcn/modules/deform_conv.py
deteasypaddleocr/custom_easyocr/DBNet/assets/ops/dcn/modules/deform_pool.py
deteasypaddleocr/custom_easyocr/DBNet/assets/ops/dcn/src/deform_conv_cpu.cpp
deteasypaddleocr/custom_easyocr/DBNet/assets/ops/dcn/src/deform_conv_cpu_kernel.cpp
deteasypaddleocr/custom_easyocr/DBNet/assets/ops/dcn/src/deform_conv_cpu_kernel.h
deteasypaddleocr/custom_easyocr/DBNet/assets/ops/dcn/src/deform_conv_cuda.cpp
deteasypaddleocr/custom_easyocr/DBNet/assets/ops/dcn/src/deform_conv_cuda_kernel.cu
deteasypaddleocr/custom_easyocr/DBNet/assets/ops/dcn/src/deform_pool_cpu.cpp
deteasypaddleocr/custom_easyocr/DBNet/assets/ops/dcn/src/deform_pool_cpu_kernel.cpp
deteasypaddleocr/custom_easyocr/DBNet/assets/ops/dcn/src/deform_pool_cpu_kernel.h
deteasypaddleocr/custom_easyocr/DBNet/assets/ops/dcn/src/deform_pool_cuda.cpp
deteasypaddleocr/custom_easyocr/DBNet/assets/ops/dcn/src/deform_pool_cuda_kernel.cu
deteasypaddleocr-1.1.5.dist-info/METADATA
deteasypaddleocr-1.1.5.dist-info/WHEEL
deteasypaddleocr-1.1.5.dist-info/top_level.txt
deteasypaddleocr-1.1.5.dist-info/RECORD
