Metadata-Version: 2.1
Name: deteasypaddleocr
Version: 1.1.5
Summary: OCR text detection using custom EasyOCR and PaddleOCR libraries
Requires-Python: >=3.7
Requires-Dist: opencv-python>=4.5.0
Requires-Dist: numpy>=1.19.0
Requires-Dist: matplotlib>=3.3.0
Requires-Dist: Pillow>=8.0.0
Requires-Dist: shapely>=1.7.1
Requires-Dist: PyYAML>=5.3.1
Requires-Dist: scikit-image>=0.17.2
Requires-Dist: pyclipper>=1.2.0
Requires-Dist: scipy>=1.5.4
Requires-Dist: azureml-core>=1.41.0
Provides-Extra: easyocr
Requires-Dist: torch>=1.7.0; extra == "easyocr"
Requires-Dist: torchvision>=0.8.0; extra == "easyocr"
Requires-Dist: packaging>=20.0; extra == "easyocr"
Provides-Extra: paddleocr
Requires-Dist: paddle-paddle>=2.0.0; extra == "paddleocr"
Requires-Dist: tqdm>=4.27.0; extra == "paddleocr"
Requires-Dist: imgaug>=0.4.0; extra == "paddleocr"
Requires-Dist: lmdb>=1.0.0; extra == "paddleocr"
Requires-Dist: requests>=2.22.0; extra == "paddleocr"
Requires-Dist: visualdl>=2.2.0; extra == "paddleocr"
Requires-Dist: python-Levenshtein>=0.12.2; extra == "paddleocr"
Provides-Extra: all
Requires-Dist: torch>=1.7.0; extra == "all"
Requires-Dist: torchvision>=0.8.0; extra == "all"
Requires-Dist: packaging>=20.0; extra == "all"
Requires-Dist: paddlepaddle>=2.0.0; extra == "all"
Requires-Dist: tqdm>=4.27.0; extra == "all"
Requires-Dist: imgaug>=0.4.0; extra == "all"
Requires-Dist: lmdb>=1.0.0; extra == "all"
Requires-Dist: requests>=2.22.0; extra == "all"
Requires-Dist: visualdl>=2.2.0; extra == "all"
Requires-Dist: python-Levenshtein>=0.12.2; extra == "all"
